__init__.py
event/__init__.py
event/event.py
event/event_content.py
event/event_metadata.py
eventbus/__init__.py
eventbus/async_local_eventbus.py
eventbus/eventbus.py
eventbus/exceptions.py
eventbus/queued_local_eventbus.py
eventbus/topic.py
eventbus_client/__init__.py
eventbus_client/local_eventbus_client.py
eventbus_client/publisher/__init__.py
eventbus_client/publisher/local_eventbus_publisher.py
eventbus_client/publisher/publisher.py
eventbus_client/subscriber/__init__.py
eventbus_client/subscriber/closure_subscriber.py
eventbus_client/subscriber/local_eventbus_closure_subscriber.py
eventbus_client/subscriber/local_eventbus_subscriber.py
eventbus_client/subscriber/subscriber.py
py_busline-0.2.0.dist-info/LICENSE
py_busline-0.2.0.dist-info/METADATA
py_busline-0.2.0.dist-info/WHEEL
py_busline-0.2.0.dist-info/top_level.txt
py_busline-0.2.0.dist-info/RECORD
