Metadata-Version: 2.1
Name: py-busline
Version: 0.2.0
Summary: Agnostic eventbus for Python
Author-email: Nicola Ricciardi <ricciardincl@gmail.com>
Project-URL: Homepage, https://github.com/nricciardi/py-busline
Project-URL: Issues, https://github.com/nricciardi/py-busline/issues
Classifier: Programming Language :: Python :: 3
Classifier: License :: OSI Approved :: GNU General Public License v3 (GPLv3)
Classifier: Operating System :: OS Independent
Requires-Python: >=3.8
License-File: LICENSE
